embedded/fpga/FPGA_BLP_V3_BB_MAX1000_01_00/src/SPI_RGB/HOST_MUX/HOST_MUX.v
////////////////////////////////////////////////////////////////////////////////////////////
module HOST_MUX (
	input CLK,
	input CLK_1kHz,
	input [255:0] DATA_1,
	input DATA_WRITE_COPY_1,
	input [7:0] BANK_1,
	input [255:0] DATA_2,
	input DATA_WRITE_COPY_2,
	input [7:0] BANK_2,
	output reg [255:0] DATA,
	output reg DATA_WRITE_COPY,
	output reg [7:0] BANK
	);
	//
	reg [15:0] counter;
	reg hri1; reg hri2; reg hri3; reg hri4; reg hri5; reg hri6;
	//
	parameter MUX_DELAY = 16'd1000;
	// Glue Logic
	assign copy_1_re = hri1 && !hri2;
	assign copy_1_fe = !hri1 && hri2;
	assign copy_2_re = hri3 && !hri4;
	assign copy_2_fe = !hri3 && hri4;
	assign clk_1kHz_re = hri5 && !hri6;
	assign clk_1kHz_fe = !hri5 && hri6;
	//	
	initial
	begin
		DATA_WRITE_COPY <= 0;
		BANK <= 0;
		DATA <= 0;	
		//
		counter <= 0;
		hri1 <= 0; hri2 <= 0; hri3 <= 0; hri4 <= 0; hri5 <= 0; hri6 <= 0;
	end	
	//
	always	@(posedge CLK)
	begin
	//
	hri1 <= DATA_WRITE_COPY_1;
	hri2 <= hri1;			
	hri3 <= DATA_WRITE_COPY_2;
	hri4 <= hri3;	
	hri5 <= CLK_1kHz;
	hri6 <= hri5;	
	//
	if (DATA_WRITE_COPY)
		DATA_WRITE_COPY <= 0;
	//
	if (clk_1kHz_re && (counter > 0))
		counter <= counter - 1;
	//
	if (copy_1_re && (counter == 0))
		begin
		DATA <= DATA_1;
		BANK <= BANK_1;
		end
	if (copy_1_fe && (counter == 0))
		DATA_WRITE_COPY <= 1;
	//
	if (copy_2_re)
		begin
		counter <= MUX_DELAY;
		DATA <= DATA_2;
		BANK <= BANK_2;
		end
	if (copy_2_fe)
		DATA_WRITE_COPY <= 1;
	//
end
endmodule
////////////////////////////////////////////////////////////////////////////////////////////

embedded/fpga/FPGA_BLP_V3_BB_MAX1000_01_00/src/SPI_RGB/HOST_MUX/ICARUS_TB.v
`include "HOST_MUX.v"
// http://verilogtutorial.blogspot.ch/2012/09/verilog-timescale-system-tasks.html
`timescale 10ns/1ns
//
module ICARUS_TB;
	// SPI_HOST
	integer file;
	reg clk;
	reg clk_1kHz;
	reg [255:0] data_1;	
	reg [7:0] bank_1;	
	reg data_write_copy_1;
	reg [255:0] data_2;	
	reg [7:0] bank_2;	
	reg data_write_copy_2;
	wire [255:0] data;	
	wire [7:0] bank;	
	wire data_write_copy;
	//
	initial 
		begin
			clk <= 1;		
			clk_1kHz <= 1;		
			bank_1 <= 0;
			data_1 <= 0;
			data_write_copy_1 <= 0;
			bank_2 <= 0;
			data_2 <= 0;
			data_write_copy_2 <= 0;
			//
			$dumpfile("vcd\\\icarus_tb.vcd"); 
			$dumpvars(0, ICARUS_TB); 
			//
			#2 data_write_copy_2 <= 1;
			#2 data_write_copy_2 <= 0;
			//
			#8 bank_1 <= 1;
			#0 data_1 <= 1;
			#2 data_write_copy_1 <= 1;
			#2 data_write_copy_1 <= 0;
			//
			#8 bank_2 <= 2;
			#0 data_2 <= 2;
			#2 data_write_copy_2 <= 1;
			#2 data_write_copy_2 <= 0;
			//
			#20 $finish; 
		end 
	//
	always #1 clk <= !clk;
	always #10 clk_1kHz <= !clk_1kHz;
	//
	HOST_MUX host_mux(clk, 
	                  clk_1kHz,
	                  data_1, 
					  data_write_copy_1, 
					  bank_1, 
					  data_2, 
					  data_write_copy_2, 
					  bank_2, 					 
					  data, 
					  data_write_copy, 
					  bank);
	//
endmodule
//
/*
cd D:\Dropbox\ABBTS_LABOR_DOZ\MOTION_CONTROL\FPGA\QUARTUS\FPGA_MODUL_MAX1000_00_12\src\SPI_FPGA_HOST
C:\iverilog\bin\iverilog -s ICARUS_TB -o icarus_tb.o ICARUS_TB.v
C:\iverilog\bin\vvp icarus_tb.o
*/

embedded/fpga/FPGA_BLP_V3_BB_MAX1000_01_00/src/SPI_RGB/HOST_MUX/vcd/icarus_tb.vcd
$date
	Wed May 04 12:57:06 2022
$end
$version
	Icarus Verilog
$end
$timescale
	1ns
$end
$scope module ICARUS_TB $end
$var wire 1 ! data_write_copy $end
$var wire 256 " data [255:0] $end
$var wire 8 # bank [7:0] $end
$var reg 8 $ bank_1 [7:0] $end
$var reg 8 % bank_2 [7:0] $end
$var reg 1 & clk $end
$var reg 1 ' clk_1kHz $end
$var reg 256 ( data_1 [255:0] $end
$var reg 256 ) data_2 [255:0] $end
$var reg 1 * data_write_copy_1 $end
$var reg 1 + data_write_copy_2 $end
$scope module host_mux $end
$var wire 8 , BANK_1 [7:0] $end
$var wire 8 - BANK_2 [7:0] $end
$var wire 1 & CLK $end
$var wire 1 ' CLK_1kHz $end
$var wire 256 . DATA_1 [255:0] $end
$var wire 256 / DATA_2 [255:0] $end
$var wire 1 * DATA_WRITE_COPY_1 $end
$var wire 1 + DATA_WRITE_COPY_2 $end
$var wire 1 0 clk_1kHz_fe $end
$var wire 1 1 clk_1kHz_re $end
$var wire 1 2 copy_1_fe $end
$var wire 1 3 copy_1_re $end
$var wire 1 4 copy_2_fe $end
$var wire 1 5 copy_2_re $end
$var reg 8 6 BANK [7:0] $end
$var reg 256 7 DATA [255:0] $end
$var reg 1 ! DATA_WRITE_COPY $end
$var reg 16 8 counter [15:0] $end
$var reg 1 9 hri1 $end
$var reg 1 : hri2 $end
$var reg 1 ; hri3 $end
$var reg 1 < hri4 $end
$var reg 1 = hri5 $end
$var reg 1 > hri6 $end
$upscope $end
$upscope $end
$enddefinitions $end
#0
$dumpvars
0>
1=
0<
0;
0:
09
b0 8
b0 7
b0 6
05
04
03
02
11
00
b0 /
b0 .
b0 -
b0 ,
0+
0*
b0 )
b0 (
1'
1&
b0 %
b0 $
b0 #
b0 "
0!
$end
#10
0&
#20
01
15
1>
1;
1&
1+
#30
0&
#40
14
05
b1111101000 8
1<
0;
1&
0+
#50
0&
#60
04
1!
0<
1&
#70
0&
#80
0!
1&
#90
0&
#100
10
0=
1&
0'
#110
0&
#120
00
0>
b1 (
b1 .
1&
b1 $
b1 ,
#130
0&
#140
13
19
1&
1*
#150
0&
#160
12
03
1:
09
1&
0*
#170
0&
#180
02
0:
1&
#190
0&
#200
11
1=
1&
1'
#210
0&
#220
01
b1111100111 8
1>
1&
#230
0&
#240
b10 )
b10 /
1&
b10 %
b10 -
#250
0&
#260
15
1;
1&
1+
#270
0&
#280
14
05
b10 #
b10 6
b10 "
b10 7
b1111101000 8
1<
0;
1&
0+
#290
0&
#300
10
04
1!
0=
0<
1&
0'
#310
0&
#320
00
0!
0>
1&
#330
0&
#340
1&
#350
0&
#360
1&
#370
0&
#380
1&
#390
0&
#400
11
1=
1&
1'
#410
0&
#420
01
b1111100111 8
1>
1&
