embedded/fpga/FPGA_BLP_V3_BB_MAX1000_01_00/src/SPI_RGB/HOST/SPI_HOST_RGB.v
////////////////////////////////////////////////////////////////////////////////////////////
module SPI_HOST_RGB (
	input CLK,
	input SPI_CS,
	input SPI_CLK,
	input SPI_MOSI,
	output reg [255:0] DATA_OUT,
	output reg DATA_WRITE_COPY,
	output reg [7:0] BANK
	);
	//
	reg [0:7] cmd_temp;// LSB
	reg [0:7] bank_temp;// LSB	
	reg [255:0] data_out_temp;		
	reg [11:0] spi_clk_ctr;
	reg [11:0] i_cmd;
	reg [11:0] i_bank;		
	reg [11:0] i_wait;		
	reg [11:0] i_data_mosi;
	reg spi_activ;
	reg hri1; reg hri2; reg hri3; reg hri4;
	//
	wire spi_cs_fe;
	wire spi_cs_re;
	wire spi_clk_re;
	wire spi_clk_fe;
	// Filter der Eingaenge
	wire spi_cs_filter;
	wire spi_clk_filter;
	wire spi_mosi_filter;	
	wire spi_write_rgb;
	
	parameter SPI_FILTER = 5'd5;
	SPI_INP_FILTER_RGB_HOST spi_inp_filter_cs(CLK, SPI_CS, spi_cs_filter);       defparam spi_inp_filter_cs.FILTER = SPI_FILTER;
	SPI_INP_FILTER_RGB_HOST spi_inp_filter_clk(CLK, SPI_CLK, spi_clk_filter);    defparam spi_inp_filter_clk.FILTER = SPI_FILTER;
	SPI_INP_FILTER_RGB_HOST spi_inp_filter_mosi(CLK, SPI_MOSI, spi_mosi_filter); defparam spi_inp_filter_mosi.FILTER = SPI_FILTER;
	// Glue Logic
	assign spi_write_rgb = spi_activ & cmd_temp[0] & cmd_temp[3];// ENABLE, READ, WRITE RGB
	assign spi_cs_re = (hri1 && !hri2);
	assign spi_cs_fe = (!hri1 && hri2);
	assign spi_clk_re = (hri3 && !hri4 && spi_activ);
	assign spi_clk_fe = (!hri3 && hri4 && spi_activ);
	//	
	initial
	begin
		DATA_WRITE_COPY <= 0;
		BANK <= 0;
		DATA_OUT <= 0;	
		//
		spi_activ <= 0;
		cmd_temp <= 0;
		bank_temp <= 0;
		data_out_temp <= 0;
		spi_clk_ctr <= 0;
		i_cmd <= 0;
		i_bank <= 0;	
		i_wait <= 0;
		i_data_mosi <= 0;
		//
		hri1 <= 0; hri2 <= 0; hri3 <= 0; hri4 <= 0;		
	end	
	//
	always	@(posedge CLK)
	begin
	//
	hri1 <= spi_cs_filter;
	hri2 <= hri1;			
	//
	if (spi_cs_fe) 
		begin
		spi_activ <= 1;
		spi_clk_ctr <= 0;
		cmd_temp <= 0;
		bank_temp <= 0;
		//data_out_temp <= 0;				
		i_cmd <= 0;
		i_bank <= 0;	
		i_wait <= 0;
		i_data_mosi <= 0;
		end
	//
	// Counter SPI_CLK
	hri3 <= spi_clk_filter;
	hri4 <= hri3;
	if (spi_clk_re && (spi_clk_ctr < 280))
		begin
		spi_clk_ctr <= spi_clk_ctr + 1;
		end
	// SPI Kommunkation beendet
	if (spi_cs_re) 
		begin
		spi_activ <= 0;
		DATA_WRITE_COPY <= spi_write_rgb;// write cmd
		DATA_OUT <= data_out_temp;	
		end	
	else
		begin
		DATA_WRITE_COPY <= 0;
		end
		
	// SPI Kommunikation aktiv
	if (spi_clk_re && spi_activ)
		begin
		// Kommando und Adresse ausgeben
		if ((spi_clk_ctr == 20))
			begin
			BANK <= bank_temp;
			end
		// Kommandobyte
		if (spi_clk_ctr < 8)
			begin
			cmd_temp[i_cmd] <= spi_mosi_filter;
			i_cmd <= i_cmd + 1;
			end
		// BANK Byte
		else if (spi_clk_ctr < 16)
			begin
			bank_temp[i_bank] <= spi_mosi_filter;
			i_bank <= i_bank + 1;
			end
		// wait Byte
		else if (spi_clk_ctr < 24)
			begin
			i_wait <= i_wait + 1;
			end
		// Datenempfang
		else if (spi_clk_ctr < 280)
			begin
			if (cmd_temp[3] && (i_data_mosi < 256))
				begin
				data_out_temp[i_data_mosi] <= spi_mosi_filter;
				end
			i_data_mosi <= i_data_mosi + 1;
			end
		end
	end
endmodule
////////////////////////////////////////////////////////////////////////////////////////////
//	Digitales Filter
module	SPI_INP_FILTER_RGB_HOST (
	input CLK, 
	input IN,
	output reg OUT
	);
//
parameter FILTER = 5'd5;
//
reg [4:0] ctr0;
reg [4:0] ctr1;
//
initial
	begin
	OUT <= 0;
	ctr0 <= 0;
	ctr1 <= 0;
	end
always	@(posedge CLK)
begin
	if (IN && !OUT)
		begin
		ctr0 <= 0;
		ctr1 <= ctr1 + 1;
		end
	//	
	if (!IN && OUT)
		begin
		ctr0 <= ctr0 + 1;
		ctr1 <= 0;
		end	
	//
	if (ctr0 == FILTER)
		begin
		ctr0 <= 0;
		ctr1 <= 0;
		OUT <= 0;
		end
	//
	if (ctr1 == FILTER)
		begin
		ctr0 <= 0;
		ctr1 <= 0;
		OUT <= 1;
		end
	//	
	if (((ctr0 > 0) && IN) || ((ctr1 > 0) && !IN))
		begin
		ctr0 <= 0;
		ctr1 <= 0;
		end	
end
endmodule
////////////////////////////////////////////////////////////////////////////////////////////

embedded/fpga/FPGA_BLP_V3_BB_MAX1000_01_00/src/SPI_RGB/HOST/ICARUS_TB.v
`include "SPI_HOST_RGB.v"
// http://verilogtutorial.blogspot.ch/2012/09/verilog-timescale-system-tasks.html
`timescale 10ns/1ns
//
module ICARUS_TB;
	// SPI_HOST
	integer file;
	reg clk;
	reg spi_cs;
	reg spi_clk;
	reg spi_mosi;
	wire [255:0] data_out;	
	wire [7:0] bank;	
	wire data_write_copy;
	//
	initial 
		begin
			clk <= 1;		
			// SPI_HOST
			spi_cs <= 1;
			spi_clk <= 0;
			spi_mosi <= 0;
			//
			$dumpfile("vcd\\\icarus_tb.vcd"); 
			$dumpvars(0, ICARUS_TB); 
			//
			/*
			#4 host_master_1 <= 1;
			#2 data_read_1 <= 1;
			#2 data_read_1 <= 0;
			*/
			//
			#15 spi_cs <= 0;
			#6 spi_cs <= 1;
			#4 spi_cs <= 0;
			#2 spi_cs <= 1;
			#13 spi_cs <= 0;
			// CMD
			#30 spi_mosi <= 1;//0 => WRITE
			#50 spi_mosi <= 0;
			#30 spi_mosi <= 0;//1
			#50 spi_mosi <= 0;
			#30 spi_mosi <= 0;//2
			#50 spi_mosi <= 0;
			#30 spi_mosi <= 0;//3
			#50 spi_mosi <= 0;
			#30 spi_mosi <= 0;//4
			#50 spi_mosi <= 0;
			#30 spi_mosi <= 0;//5
			#50 spi_mosi <= 0;
			#30 spi_mosi <= 0;//6 
			#50 spi_mosi <= 0;
			#30 spi_mosi <= 0;//7 
			#50 spi_mosi <= 0;
			// BANK BYTE
			#30 spi_mosi <= 0;//0
			#50 spi_mosi <= 0;
			#30 spi_mosi <= 0;//1
			#50 spi_mosi <= 0;
			#30 spi_mosi <= 0;//2
			#50 spi_mosi <= 0;
			#30 spi_mosi <= 0;//3
			#50 spi_mosi <= 0;
			#30 spi_mosi <= 0;//4
			#50 spi_mosi <= 0;
			#30 spi_mosi <= 0;//5
			#50 spi_mosi <= 0;
			#30 spi_mosi <= 0;//6
			#50 spi_mosi <= 0;
			#30 spi_mosi <= 1;//7
			#50 spi_mosi <= 0;
			// WAIT BYTE
			#30 spi_mosi <= 0;//0
			#50 spi_mosi <= 0;
			#30 spi_mosi <= 0;//1
			#50 spi_mosi <= 0;
			#30 spi_mosi <= 0;//2
			#50 spi_mosi <= 0;
			#30 spi_mosi <= 0;//3
			#50 spi_mosi <= 0;
			#30 spi_mosi <= 0;//4
			#50 spi_mosi <= 0;
			#30 spi_mosi <= 0;//5
			#50 spi_mosi <= 0;
			#30 spi_mosi <= 0;//6
			#50 spi_mosi <= 0;
			#30 spi_mosi <= 0;//7
			#50 spi_mosi <= 0;
			// DATEN BYTE 0
			#30 spi_mosi <= 1;//0
			#50 spi_mosi <= 0;
			#30 spi_mosi <= 0;//1
			#50 spi_mosi <= 0;
			#30 spi_mosi <= 0;//2
			#50 spi_mosi <= 0;
			#30 spi_mosi <= 0;//3
			#50 spi_mosi <= 0;
			#30 spi_mosi <= 0;//4
			#50 spi_mosi <= 0;
			#30 spi_mosi <= 0;//5
			#50 spi_mosi <= 0;
			#30 spi_mosi <= 0;//6
			#50 spi_mosi <= 0;
			#30 spi_mosi <= 0;//7
			#50 spi_mosi <= 0;
			// DATEN BYTE 1
			#30 spi_mosi <= 0;//0
			#50 spi_mosi <= 0;
			#30 spi_mosi <= 0;//1
			#50 spi_mosi <= 0;
			#30 spi_mosi <= 0;//2
			#50 spi_mosi <= 0;
			#30 spi_mosi <= 0;//3
			#50 spi_mosi <= 0;
			#30 spi_mosi <= 0;//4
			#50 spi_mosi <= 0;
			#30 spi_mosi <= 0;//5
			#50 spi_mosi <= 0;
			#30 spi_mosi <= 0;//6
			#50 spi_mosi <= 0;
			#30 spi_mosi <= 0;//7
			#50 spi_mosi <= 1;			
			//
			#1979 spi_mosi <= 1;
			#50 spi_mosi <= 0;
			//
			#300 spi_cs <= 1;
			#100 spi_cs <= 0;
			#101 spi_cs <= 1;
			//
			#10 $finish; 
		end 
	//
	always #1 clk <= !clk;
	always #40 
	begin
		if (!spi_cs) spi_clk <= !spi_clk;
		else spi_clk <= 0;
	end
	//
	SPI_HOST_RGB spiHostRgb(clk, 
	                 spi_cs, 
					 spi_clk, 
					 spi_mosi, 
					 data_out, 
					 data_write_copy, 
					 bank);
	//
endmodule
//
/*
cd D:\Dropbox\ABBTS_LABOR_DOZ\MOTION_CONTROL\FPGA\QUARTUS\FPGA_MODUL_MAX1000_00_12\src\SPI_FPGA_HOST
C:\iverilog\bin\iverilog -s ICARUS_TB -o icarus_tb.o ICARUS_TB.v
C:\iverilog\bin\vvp icarus_tb.o
*/

embedded/fpga/FPGA_BLP_V3_BB_MAX1000_01_00/src/SPI_RGB/HOST/vcd/icarus_tb.vcd
$date
	Wed May 04 10:20:42 2022
$end
$version
	Icarus Verilog
$end
$timescale
	1ns
$end
$scope module ICARUS_TB $end
$var wire 1 ! data_write_copy $end
$var wire 256 " data_out [255:0] $end
$var wire 8 # bank [7:0] $end
$var reg 1 $ clk $end
$var reg 1 % spi_clk $end
$var reg 1 & spi_cs $end
$var reg 1 ' spi_mosi $end
$scope module spiHostRgb $end
$var wire 1 $ CLK $end
$var wire 1 % SPI_CLK $end
$var wire 1 & SPI_CS $end
$var wire 1 ' SPI_MOSI $end
$var wire 1 ( spi_clk_fe $end
$var wire 1 ) spi_clk_re $end
$var wire 1 * spi_cs_fe $end
$var wire 1 + spi_cs_re $end
$var wire 1 , spi_write_rgb $end
$var wire 1 - spi_mosi_filter $end
$var wire 1 . spi_cs_filter $end
$var wire 1 / spi_clk_filter $end
$var reg 8 0 BANK [7:0] $end
$var reg 256 1 DATA_OUT [255:0] $end
$var reg 1 ! DATA_WRITE_COPY $end
$var reg 8 2 bank_temp [0:7] $end
$var reg 8 3 cmd_temp [0:7] $end
$var reg 256 4 data_out_temp [255:0] $end
$var reg 1 5 hri1 $end
$var reg 1 6 hri2 $end
$var reg 1 7 hri3 $end
$var reg 1 8 hri4 $end
$var reg 12 9 i_bank [11:0] $end
$var reg 12 : i_cmd [11:0] $end
$var reg 12 ; i_data_mosi [11:0] $end
$var reg 12 < i_wait [11:0] $end
$var reg 1 = spi_activ $end
$var reg 12 > spi_clk_ctr [11:0] $end
$scope module spi_inp_filter_clk $end
$var wire 1 $ CLK $end
$var wire 1 % IN $end
$var reg 1 / OUT $end
$var reg 5 ? ctr0 [4:0] $end
$var reg 5 @ ctr1 [4:0] $end
$upscope $end
$scope module spi_inp_filter_cs $end
$var wire 1 $ CLK $end
$var wire 1 & IN $end
$var reg 1 . OUT $end
$var reg 5 A ctr0 [4:0] $end
$var reg 5 B ctr1 [4:0] $end
$upscope $end
$scope module spi_inp_filter_mosi $end
$var wire 1 $ CLK $end
$var wire 1 ' IN $end
$var reg 1 - OUT $end
$var reg 5 C ctr0 [4:0] $end
$var reg 5 D ctr1 [4:0] $end
$upscope $end
$upscope $end
$upscope $end
$enddefinitions $end
#0
$dumpvars
b0 D
b0 C
b1 B
b0 A
b0 @
b0 ?
b0 >
0=
b0 <
b0 ;
b0 :
b0 9
08
07
06
05
b0 4
b0 3
b0 2
b0 1
b0 0
0/
0.
0-
0,
0+
0*
0)
0(
0'
1&
0%
1$
b0 #
b0 "
0!
$end
#10
0$
#20
b10 B
1$
#30
0$
#40
b11 B
1$
#50
0$
#60
b100 B
1$
#70
0$
#80
b101 B
1$
#90
0$
#100
1.
b0 B
1$
#110
0$
#120
1+
15
1$
#130
0$
#140
0+
1!
16
1$
#150
0$
0&
#160
b1 A
0!
1$
#170
0$
#180
b10 A
1$
#190
0$
#200
b11 A
1$
#210
0$
1&
#220
b0 A
1$
#230
0$
#240
1$
#250
0$
0&
#260
b1 A
1$
#270
0$
1&
#280
b0 A
1$
#290
0$
#300
1$
#310
0$
#320
1$
#330
0$
#340
1$
#350
0$
#360
1$
#370
0$
#380
1$
#390
0$
#400
b1 A
1$
0&
#410
0$
#420
b10 A
1$
#430
0$
#440
b11 A
1$
#450
0$
#460
b100 A
1$
#470
0$
#480
b101 A
1$
#490
0$
#500
0.
b0 A
1$
#510
0$
#520
1*
05
1$
#530
0$
#540
0*
1=
06
1$
#550
0$
#560
1$
#570
0$
#580
1$
#590
0$
#600
1$
#610
0$
#620
1$
#630
0$
#640
1$
#650
0$
#660
1$
#670
0$
#680
1$
#690
0$
#700
b1 D
1$
1'
#710
0$
#720
b10 D
1$
#730
0$
#740
b11 D
1$
#750
0$
#760
b100 D
1$
#770
0$
#780
b101 D
1$
#790
0$
#800
b1 @
1-
b0 D
1$
1%
#810
0$
#820
b10 @
1$
#830
0$
#840
b11 @
1$
#850
0$
#860
b100 @
1$
#870
0$
#880
b101 @
1$
#890
0$
#900
1/
b0 @
1$
#910
0$
#920
1)
17
1$
#930
0$
#940
0)
b1 :
b10000000 3
b1 >
18
1$
#950
0$
#960
1$
#970
0$
#980
1$
#990
0$
#1000
1$
#1010
0$
#1020
1$
#1030
0$
#1040
1$
#1050
0$
#1060
1$
#1070
0$
#1080
1$
#1090
0$
#1100
1$
#1110
0$
#1120
1$
#1130
0$
#1140
1$
#1150
0$
#1160
1$
#1170
0$
#1180
1$
#1190
0$
#1200
b1 ?
b1 C
1$
0%
0'
#1210
0$
#1220
b10 C
b10 ?
1$
#1230
0$
#1240
b11 ?
b11 C
1$
#1250
0$
#1260
b100 C
b100 ?
1$
#1270
0$
#1280
b101 ?
b101 C
1$
#1290
0$
#1300
0-
b0 C
0/
b0 ?
1$
#1310
0$
#1320
1(
07
1$
#1330
0$
#1340
0(
08
1$
#1350
0$
#1360
1$
#1370
0$
#1380
1$
#1390
0$
#1400
1$
#1410
0$
#1420
1$
#1430
0$
#1440
1$
#1450
0$
#1460
1$
#1470
0$
#1480
1$
#1490
0$
#1500
1$
#1510
0$
#1520
1$
#1530
0$
#1540
1$
#1550
0$
#1560
1$
#1570
0$
#1580
1$
#1590
0$
#1600
b1 @
1$
1%
#1610
0$
#1620
b10 @
1$
#1630
0$
#1640
b11 @
1$
#1650
0$
#1660
b100 @
1$
#1670
0$
#1680
b101 @
1$
#1690
0$
#1700
1/
b0 @
1$
#1710
0$
#1720
1)
17
1$
#1730
0$
#1740
0)
b10 :
b10 >
18
1$
#1750
0$
#1760
1$
#1770
0$
#1780
1$
#1790
0$
#1800
1$
#1810
0$
#1820
1$
#1830
0$
#1840
1$
#1850
0$
#1860
1$
#1870
0$
#1880
1$
#1890
0$
#1900
1$
#1910
0$
#1920
1$
#1930
0$
#1940
1$
#1950
0$
#1960
1$
#1970
0$
#1980
1$
#1990
0$
#2000
b1 ?
1$
0%
#2010
0$
#2020
b10 ?
1$
#2030
0$
#2040
b11 ?
1$
#2050
0$
#2060
b100 ?
1$
#2070
0$
#2080
b101 ?
1$
#2090
0$
#2100
0/
b0 ?
1$
#2110
0$
#2120
1(
07
1$
#2130
0$
#2140
0(
08
1$
#2150
0$
#2160
1$
#2170
0$
#2180
1$
#2190
0$
#2200
1$
#2210
0$
#2220
1$
#2230
0$
#2240
1$
#2250
0$
#2260
1$
#2270
0$
#2280
1$
#2290
0$
#2300
1$
#2310
0$
#2320
1$
#2330
0$
#2340
1$
#2350
0$
#2360
1$
#2370
0$
#2380
1$
#2390
0$
#2400
b1 @
1$
1%
#2410
0$
#2420
b10 @
1$
#2430
0$
#2440
b11 @
1$
#2450
0$
#2460
b100 @
1$
#2470
0$
#2480
b101 @
1$
#2490
0$
#2500
1/
b0 @
1$
#2510
0$
#2520
1)
17
1$
#2530
0$
#2540
0)
b11 :
b11 >
18
1$
#2550
0$
#2560
1$
#2570
0$
#2580
1$
#2590
0$
#2600
1$
#2610
0$
#2620
1$
#2630
0$
#2640
1$
#2650
0$
#2660
1$
#2670
0$
#2680
1$
#2690
0$
#2700
1$
#2710
0$
#2720
1$
#2730
0$
#2740
1$
#2750
0$
#2760
1$
#2770
0$
#2780
1$
#2790
0$
#2800
b1 ?
1$
0%
#2810
0$
#2820
b10 ?
1$
#2830
0$
#2840
b11 ?
1$
#2850
0$
#2860
b100 ?
1$
#2870
0$
#2880
b101 ?
1$
#2890
0$
#2900
0/
b0 ?
1$
#2910
0$
#2920
1(
07
1$
#2930
0$
#2940
0(
08
1$
#2950
0$
#2960
1$
#2970
0$
#2980
1$
#2990
0$
#3000
1$
#3010
0$
#3020
1$
#3030
0$
#3040
1$
#3050
0$
#3060
1$
#3070
0$
#3080
1$
#3090
0$
#3100
1$
#3110
0$
#3120
1$
#3130
0$
#3140
1$
#3150
0$
#3160
1$
#3170
0$
#3180
1$
#3190
0$
#3200
b1 @
1$
1%
#3210
0$
#3220
b10 @
1$
#3230
0$
#3240
b11 @
1$
#3250
0$
#3260
b100 @
1$
#3270
0$
#3280
b101 @
1$
#3290
0$
#3300
1/
b0 @
1$
#3310
0$
#3320
1)
17
1$
#3330
0$
#3340
0)
b100 :
b100 >
18
1$
#3350
0$
#3360
1$
#3370
0$
#3380
1$
#3390
0$
#3400
1$
#3410
0$
#3420
1$
#3430
0$
#3440
1$
#3450
0$
#3460
1$
#3470
0$
#3480
1$
#3490
0$
#3500
1$
#3510
0$
#3520
1$
#3530
0$
#3540
1$
#3550
0$
#3560
1$
#3570
0$
#3580
1$
#3590
0$
#3600
b1 ?
1$
0%
#3610
0$
#3620
b10 ?
1$
#3630
0$
#3640
b11 ?
1$
#3650
0$
#3660
b100 ?
1$
#3670
0$
#3680
b101 ?
1$
#3690
0$
#3700
0/
b0 ?
1$
#3710
0$
#3720
1(
07
1$
#3730
0$
#3740
0(
08
1$
#3750
0$
#3760
1$
#3770
0$
#3780
1$
#3790
0$
#3800
1$
#3810
0$
#3820
1$
#3830
0$
#3840
1$
#3850
0$
#3860
1$
#3870
0$
#3880
1$
#3890
0$
#3900
1$
#3910
0$
#3920
1$
#3930
0$
#3940
1$
#3950
0$
#3960
1$
#3970
0$
#3980
1$
#3990
0$
#4000
b1 @
1$
1%
#4010
0$
#4020
b10 @
1$
#4030
0$
#4040
b11 @
1$
#4050
0$
#4060
b100 @
1$
#4070
0$
#4080
b101 @
1$
#4090
0$
#4100
1/
b0 @
1$
#4110
0$
#4120
1)
17
1$
#4130
0$
#4140
0)
b101 :
b101 >
18
1$
#4150
0$
#4160
1$
#4170
0$
#4180
1$
#4190
0$
#4200
1$
#4210
0$
#4220
1$
#4230
0$
#4240
1$
#4250
0$
#4260
1$
#4270
0$
#4280
1$
#4290
0$
#4300
1$
#4310
0$
#4320
1$
#4330
0$
#4340
1$
#4350
0$
#4360
1$
#4370
0$
#4380
1$
#4390
0$
#4400
b1 ?
1$
0%
#4410
0$
#4420
b10 ?
1$
#4430
0$
#4440
b11 ?
1$
#4450
0$
#4460
b100 ?
1$
#4470
0$
#4480
b101 ?
1$
#4490
0$
#4500
0/
b0 ?
1$
#4510
0$
#4520
1(
07
1$
#4530
0$
#4540
0(
08
1$
#4550
0$
#4560
1$
#4570
0$
#4580
1$
#4590
0$
#4600
1$
#4610
0$
#4620
1$
#4630
0$
#4640
1$
#4650
0$
#4660
1$
#4670
0$
#4680
1$
#4690
0$
#4700
1$
#4710
0$
#4720
1$
#4730
0$
#4740
1$
#4750
0$
#4760
1$
#4770
0$
#4780
1$
#4790
0$
#4800
b1 @
1$
1%
#4810
0$
#4820
b10 @
1$
#4830
0$
#4840
b11 @
1$
#4850
0$
#4860
b100 @
1$
#4870
0$
#4880
b101 @
1$
#4890
0$
#4900
1/
b0 @
1$
#4910
0$
#4920
1)
17
1$
#4930
0$
#4940
0)
b110 :
b110 >
18
1$
#4950
0$
#4960
1$
#4970
0$
#4980
1$
#4990
0$
#5000
1$
#5010
0$
#5020
1$
#5030
0$
#5040
1$
#5050
0$
#5060
1$
#5070
0$
#5080
1$
#5090
0$
#5100
1$
#5110
0$
#5120
1$
#5130
0$
#5140
1$
#5150
0$
#5160
1$
#5170
0$
#5180
1$
#5190
0$
#5200
b1 ?
1$
0%
#5210
0$
#5220
b10 ?
1$
#5230
0$
#5240
b11 ?
1$
#5250
0$
#5260
b100 ?
1$
#5270
0$
#5280
b101 ?
1$
#5290
0$
#5300
0/
b0 ?
1$
#5310
0$
#5320
1(
07
1$
#5330
0$
#5340
0(
08
1$
#5350
0$
#5360
1$
#5370
0$
#5380
1$
#5390
0$
#5400
1$
#5410
0$
#5420
1$
#5430
0$
#5440
1$
#5450
0$
#5460
1$
#5470
0$
#5480
1$
#5490
0$
#5500
1$
#5510
0$
#5520
1$
#5530
0$
#5540
1$
#5550
0$
#5560
1$
#5570
0$
#5580
1$
#5590
0$
#5600
b1 @
1$
1%
#5610
0$
#5620
b10 @
1$
#5630
0$
#5640
b11 @
1$
#5650
0$
#5660
b100 @
1$
#5670
0$
#5680
b101 @
1$
#5690
0$
#5700
1/
b0 @
1$
#5710
0$
#5720
1)
17
1$
#5730
0$
#5740
0)
b111 :
b111 >
18
1$
#5750
0$
#5760
1$
#5770
0$
#5780
1$
#5790
0$
#5800
1$
#5810
0$
#5820
1$
#5830
0$
#5840
1$
#5850
0$
#5860
1$
#5870
0$
#5880
1$
#5890
0$
#5900
1$
#5910
0$
#5920
1$
#5930
0$
#5940
1$
#5950
0$
#5960
1$
#5970
0$
#5980
1$
#5990
0$
#6000
b1 ?
1$
0%
#6010
0$
#6020
b10 ?
1$
#6030
0$
#6040
b11 ?
1$
#6050
0$
#6060
b100 ?
1$
#6070
0$
#6080
b101 ?
1$
#6090
0$
#6100
0/
b0 ?
1$
#6110
0$
#6120
1(
07
1$
#6130
0$
#6140
0(
08
1$
#6150
0$
#6160
1$
#6170
0$
#6180
1$
#6190
0$
#6200
1$
#6210
0$
#6220
1$
#6230
0$
#6240
1$
#6250
0$
#6260
1$
#6270
0$
#6280
1$
#6290
0$
#6300
1$
#6310
0$
#6320
1$
#6330
0$
#6340
1$
#6350
0$
#6360
1$
#6370
0$
#6380
1$
#6390
0$
#6400
b1 @
1$
1%
#6410
0$
#6420
b10 @
1$
#6430
0$
#6440
b11 @
1$
#6450
0$
#6460
b100 @
1$
#6470
0$
#6480
b101 @
1$
#6490
0$
#6500
1/
b0 @
1$
#6510
0$
#6520
1)
17
1$
#6530
0$
#6540
0)
b1000 :
b1000 >
18
1$
#6550
0$
#6560
1$
#6570
0$
#6580
1$
#6590
0$
#6600
1$
#6610
0$
#6620
1$
#6630
0$
#6640
1$
#6650
0$
#6660
1$
#6670
0$
#6680
1$
#6690
0$
#6700
1$
#6710
0$
#6720
1$
#6730
0$
#6740
1$
#6750
0$
#6760
1$
#6770
0$
#6780
1$
#6790
0$
#6800
b1 ?
1$
0%
#6810
0$
#6820
b10 ?
1$
#6830
0$
#6840
b11 ?
1$
#6850
0$
#6860
b100 ?
1$
#6870
0$
#6880
b101 ?
1$
#6890
0$
#6900
0/
b0 ?
1$
#6910
0$
#6920
1(
07
1$
#6930
0$
#6940
0(
08
1$
#6950
0$
#6960
1$
#6970
0$
#6980
1$
#6990
0$
#7000
1$
#7010
0$
#7020
1$
#7030
0$
#7040
1$
#7050
0$
#7060
1$
#7070
0$
#7080
1$
#7090
0$
#7100
1$
#7110
0$
#7120
1$
#7130
0$
#7140
1$
#7150
0$
#7160
1$
#7170
0$
#7180
1$
#7190
0$
#7200
b1 @
1$
1%
#7210
0$
#7220
b10 @
1$
#7230
0$
#7240
b11 @
1$
#7250
0$
#7260
b100 @
1$
#7270
0$
#7280
b101 @
1$
#7290
0$
#7300
1/
b0 @
1$
#7310
0$
#7320
1)
17
1$
#7330
0$
#7340
0)
b1 9
b1001 >
18
1$
#7350
0$
#7360
1$
#7370
0$
#7380
1$
#7390
0$
#7400
1$
#7410
0$
#7420
1$
#7430
0$
#7440
1$
#7450
0$
#7460
1$
#7470
0$
#7480
1$
#7490
0$
#7500
1$
#7510
0$
#7520
1$
#7530
0$
#7540
1$
#7550
0$
#7560
1$
#7570
0$
#7580
1$
#7590
0$
#7600
b1 ?
1$
0%
#7610
0$
#7620
b10 ?
1$
#7630
0$
#7640
b11 ?
1$
#7650
0$
#7660
b100 ?
1$
#7670
0$
#7680
b101 ?
1$
#7690
0$
#7700
0/
b0 ?
1$
#7710
0$
#7720
1(
07
1$
#7730
0$
#7740
0(
08
1$
#7750
0$
#7760
1$
#7770
0$
#7780
1$
#7790
0$
#7800
1$
#7810
0$
#7820
1$
#7830
0$
#7840
1$
#7850
0$
#7860
1$
#7870
0$
#7880
1$
#7890
0$
#7900
1$
#7910
0$
#7920
1$
#7930
0$
#7940
1$
#7950
0$
#7960
1$
#7970
0$
#7980
1$
#7990
0$
#8000
b1 @
1$
1%
#8010
0$
#8020
b10 @
1$
#8030
0$
#8040
b11 @
1$
#8050
0$
#8060
b100 @
1$
#8070
0$
#8080
b101 @
1$
#8090
0$
#8100
1/
b0 @
1$
#8110
0$
#8120
1)
17
1$
#8130
0$
#8140
0)
b10 9
b1010 >
18
1$
#8150
0$
#8160
1$
#8170
0$
#8180
1$
#8190
0$
#8200
1$
#8210
0$
#8220
1$
#8230
0$
#8240
1$
#8250
0$
#8260
1$
#8270
0$
#8280
1$
#8290
0$
#8300
1$
#8310
0$
#8320
1$
#8330
0$
#8340
1$
#8350
0$
#8360
1$
#8370
0$
#8380
1$
#8390
0$
#8400
b1 ?
1$
0%
#8410
0$
#8420
b10 ?
1$
#8430
0$
#8440
b11 ?
1$
#8450
0$
#8460
b100 ?
1$
#8470
0$
#8480
b101 ?
1$
#8490
0$
#8500
0/
b0 ?
1$
#8510
0$
#8520
1(
07
1$
#8530
0$
#8540
0(
08
1$
#8550
0$
#8560
1$
#8570
0$
#8580
1$
#8590
0$
#8600
1$
#8610
0$
#8620
1$
#8630
0$
#8640
1$
#8650
0$
#8660
1$
#8670
0$
#8680
1$
#8690
0$
#8700
1$
#8710
0$
#8720
1$
#8730
0$
#8740
1$
#8750
0$
#8760
1$
#8770
0$
#8780
1$
#8790
0$
#8800
b1 @
1$
1%
#8810
0$
#8820
b10 @
1$
#8830
0$
#8840
b11 @
1$
#8850
0$
#8860
b100 @
1$
#8870
0$
#8880
b101 @
1$
#8890
0$
#8900
1/
b0 @
1$
#8910
0$
#8920
1)
17
1$
#8930
0$
#8940
0)
b11 9
b1011 >
18
1$
#8950
0$
#8960
1$
#8970
0$
#8980
1$
#8990
0$
#9000
1$
#9010
0$
#9020
1$
#9030
0$
#9040
1$
#9050
0$
#9060
1$
#9070
0$
#9080
1$
#9090
0$
#9100
1$
#9110
0$
#9120
1$
#9130
0$
#9140
1$
#9150
0$
#9160
1$
#9170
0$
#9180
1$
#9190
0$
#9200
b1 ?
1$
0%
#9210
0$
#9220
b10 ?
1$
#9230
0$
#9240
b11 ?
1$
#9250
0$
#9260
b100 ?
1$
#9270
0$
#9280
b101 ?
1$
#9290
0$
#9300
0/
b0 ?
1$
#9310
0$
#9320
1(
07
1$
#9330
0$
#9340
0(
08
1$
#9350
0$
#9360
1$
#9370
0$
#9380
1$
#9390
0$
#9400
1$
#9410
0$
#9420
1$
#9430
0$
#9440
1$
#9450
0$
#9460
1$
#9470
0$
#9480
1$
#9490
0$
#9500
1$
#9510
0$
#9520
1$
#9530
0$
#9540
1$
#9550
0$
#9560
1$
#9570
0$
#9580
1$
#9590
0$
#9600
b1 @
1$
1%
#9610
0$
#9620
b10 @
1$
#9630
0$
#9640
b11 @
1$
#9650
0$
#9660
b100 @
1$
#9670
0$
#9680
b101 @
1$
#9690
0$
#9700
1/
b0 @
1$
#9710
0$
#9720
1)
17
1$
#9730
0$
#9740
0)
b100 9
b1100 >
18
1$
#9750
0$
#9760
1$
#9770
0$
#9780
1$
#9790
0$
#9800
1$
#9810
0$
#9820
1$
#9830
0$
#9840
1$
#9850
0$
#9860
1$
#9870
0$
#9880
1$
#9890
0$
#9900
1$
#9910
0$
#9920
1$
#9930
0$
#9940
1$
#9950
0$
#9960
1$
#9970
0$
#9980
1$
#9990
0$
#10000
b1 ?
1$
0%
#10010
0$
#10020
b10 ?
1$
#10030
0$
#10040
b11 ?
1$
#10050
0$
#10060
b100 ?
1$
#10070
0$
#10080
b101 ?
1$
#10090
0$
#10100
0/
b0 ?
1$
#10110
0$
#10120
1(
07
1$
#10130
0$
#10140
0(
08
1$
#10150
0$
#10160
1$
#10170
0$
#10180
1$
#10190
0$
#10200
1$
#10210
0$
#10220
1$
#10230
0$
#10240
1$
#10250
0$
#10260
1$
#10270
0$
#10280
1$
#10290
0$
#10300
1$
#10310
0$
#10320
1$
#10330
0$
#10340
1$
#10350
0$
#10360
1$
#10370
0$
#10380
1$
#10390
0$
#10400
b1 @
1$
1%
#10410
0$
#10420
b10 @
1$
#10430
0$
#10440
b11 @
1$
#10450
0$
#10460
b100 @
1$
#10470
0$
#10480
b101 @
1$
#10490
0$
#10500
1/
b0 @
1$
#10510
0$
#10520
1)
17
1$
