embedded/fpga/FPGA_BLP_V3_BB_MAX1000_01_00/src/UART/UART.v
////////////////////////////////////////////////////////////////////////////////////////////
module UART( 
	input CLK,
	input RXD,
	output reg [255:0] DATA_OUT,
	output reg DATA_WRITE_COPY,
	output reg [7:0] BANK
	);
	//
	reg [7:0] byte_ctr;
	reg [7:0] byte_even;
	reg [7:0] byte_odd;
	reg [7:0] byte_even_odd;
	reg [7:0] bit_offset;
	reg uart_frg;
	reg [3:0] write_data;
	//
	wire [7:0] byte_value;
	wire done;
	//
	UART_RXD_BYTE uart_rxd_byte(CLK, RXD, byte_value, done);
	//
	initial
	begin
		DATA_OUT <= 0;
		DATA_WRITE_COPY <= 0;
		BANK <= 0;
		//
		byte_even <= 0;
		byte_odd <= 0;
		byte_even_odd <= 0;
		byte_ctr <= 0;
		bit_offset <= 0;
		uart_frg <= 0;
		write_data <= 0;
	end
	//
	always	@(posedge CLK)
	begin
		if (done)
			begin
			if (byte_value == 8'h3C) /* ascii < */
				begin
				uart_frg <= 1;
				byte_ctr <= 0;
				bit_offset <= 0;
				DATA_OUT <= 0;
				BANK <= 0;
				end
			if (byte_value == 8'h3E) /* ascii > */
				begin
				uart_frg <= 0;
				byte_ctr <= 0;
				DATA_WRITE_COPY <= 1;
				end
			end
		//
		if (DATA_WRITE_COPY) DATA_WRITE_COPY <= 0;
		//
		if (uart_frg && done)
			begin
			if ((byte_ctr % 2) == 0)
				begin
				byte_even <= byte_value;
				byte_ctr <= byte_ctr + 1;
				write_data <= 0;
				end
			else
				begin
				byte_odd <= byte_value;
				write_data <= 1;
				end
			//
			end
		//
		if (write_data == 1)
			begin
			case (byte_even)
				8'h30: byte_even_odd <= 8'h00;// 0
				8'h31: byte_even_odd <= 8'h10;// 1
				8'h32: byte_even_odd <= 8'h20;// 2
				8'h33: byte_even_odd <= 8'h30;// 3
				8'h34: byte_even_odd <= 8'h40;// 4
				8'h35: byte_even_odd <= 8'h50;// 5
				8'h36: byte_even_odd <= 8'h60;// 6
				8'h37: byte_even_odd <= 8'h70;// 7
				8'h38: byte_even_odd <= 8'h80;// 8
				8'h39: byte_even_odd <= 8'h90;// 9
				8'h61: byte_even_odd <= 8'ha0;// a
				8'h62: byte_even_odd <= 8'hb0;// b
				8'h63: byte_even_odd <= 8'hc0;// c
				8'h64: byte_even_odd <= 8'hd0;// d
				8'h65: byte_even_odd <= 8'he0;// e
				8'h66: byte_even_odd <= 8'hf0;// f
				8'h41: byte_even_odd <= 8'ha0;// A
				8'h42: byte_even_odd <= 8'hb0;// B
				8'h43: byte_even_odd <= 8'hc0;// C
				8'h44: byte_even_odd <= 8'hd0;// D
				8'h45: byte_even_odd <= 8'he0;// E
				8'h46: byte_even_odd <= 8'hf0;// F
				default: byte_even_odd <= 8'h00;
			endcase
			write_data <= 2;
			end
		//
		if (write_data == 2)
			begin
			case (byte_odd)
				8'h30: byte_even_odd[3:0] <= 4'h0;// 0
				8'h31: byte_even_odd[3:0] <= 4'h1;// 1
				8'h32: byte_even_odd[3:0] <= 4'h2;// 2
				8'h33: byte_even_odd[3:0] <= 4'h3;// 3
				8'h34: byte_even_odd[3:0] <= 4'h4;// 4
				8'h35: byte_even_odd[3:0] <= 4'h5;// 5
				8'h36: byte_even_odd[3:0] <= 4'h6;// 6
				8'h37: byte_even_odd[3:0] <= 4'h7;// 7
				8'h38: byte_even_odd[3:0] <= 4'h8;// 8
				8'h39: byte_even_odd[3:0] <= 4'h9;// 9
				8'h61: byte_even_odd[3:0] <= 4'ha;// a
				8'h62: byte_even_odd[3:0] <= 4'hb;// b
				8'h63: byte_even_odd[3:0] <= 4'hc;// c
				8'h64: byte_even_odd[3:0] <= 4'hd;// d
				8'h65: byte_even_odd[3:0] <= 4'he;// e
				8'h66: byte_even_odd[3:0] <= 4'hf;// f
				8'h41: byte_even_odd[3:0] <= 4'ha;// A
				8'h42: byte_even_odd[3:0] <= 4'hb;// B
				8'h43: byte_even_odd[3:0] <= 4'hc;// C
				8'h44: byte_even_odd[3:0] <= 4'hd;// D
				8'h45: byte_even_odd[3:0] <= 4'he;// E
				8'h46: byte_even_odd[3:0] <= 4'hf;// F
				default: byte_even_odd <= 8'h00;
			endcase
			write_data <= 3;
			end
		//
		if (write_data == 3)
			begin
			//bit_offset <= bit_offset + 8;
			write_data <= 4;
			end
		//
		if (write_data == 4)
			begin
			if (byte_ctr == 1)
				begin
				BANK <= byte_even_odd;
				end
			else
				begin
				bit_offset <= bit_offset + 8;
				DATA_OUT[bit_offset + 0] <= byte_even_odd[7];
				DATA_OUT[bit_offset + 1] <= byte_even_odd[6];
				DATA_OUT[bit_offset + 2] <= byte_even_odd[5];
				DATA_OUT[bit_offset + 3] <= byte_even_odd[4];
				DATA_OUT[bit_offset + 4] <= byte_even_odd[3];
				DATA_OUT[bit_offset + 5] <= byte_even_odd[2];
				DATA_OUT[bit_offset + 6] <= byte_even_odd[1];	
				DATA_OUT[bit_offset + 7] <= byte_even_odd[0];
				end
			byte_ctr <= byte_ctr + 1;
			write_data <= 0;
			end
		//
	end
endmodule
////////////////////////////////////////////////////////////////////////////////////////////
module UART_RXD_BYTE( 
	input CLK,
	input RXD,
	output reg [7:0] BYTE_VALUE,
	output reg DONE
	);
	//
	reg [7:0] bit_sync_ctr;
	reg [7:0] bit_ctr;
	reg uart_frg;
	reg latch_bit;
	//
	reg hri1, hri2;
	wire imp_start;	
	wire rxd_;
	//
	UART_INP_FILTER uart_inp_filter(CLK, RXD, rxd_); defparam uart_inp_filter.FILTER = 5'd1;
	//
	assign	imp_start = (!hri1 && hri2);
	//
	initial
	begin
		BYTE_VALUE <= 0;
		DONE <= 0;
		//
		bit_sync_ctr <= 0;
		bit_ctr <= 0;
		uart_frg <= 0;
		latch_bit <= 0;
		hri1 <= 0; hri2 <= 0;
	end
	//
	always	@(posedge CLK)
	begin
		hri1 <= rxd_ && !uart_frg;
		hri2 <= hri1;	
		//
		if (imp_start) 
			begin
			uart_frg <= 1;
			bit_sync_ctr <= 78;
			bit_ctr <= 0;
			BYTE_VALUE <= 0;
			end
		//
		if (bit_sync_ctr > 0) bit_sync_ctr <= bit_sync_ctr - 1;
		if ((bit_sync_ctr == 0) && uart_frg)
			begin
			BYTE_VALUE[bit_ctr] <= rxd_;
			bit_ctr <= bit_ctr + 1;
			bit_sync_ctr <= 53;
			latch_bit <= 1;
			end
		else latch_bit <= 0;
		//
		if (bit_ctr == 8)
			begin
			bit_ctr <= 0;
			DONE <= 1;
			uart_frg <= 0;
			end
		else DONE <= 0;
		//

	
	end
endmodule
////////////////////////////////////////////////////////////////////////////////////////////
//	Digitales Filter
module	UART_INP_FILTER (
	input CLK, 
	input IN,
	output reg OUT
	);
//
parameter FILTER = 5'd5;
//
reg [4:0] ctr0;
reg [4:0] ctr1;
//
initial
	begin
	OUT <= 0;
	ctr0 <= 0;
	ctr1 <= 0;
	end
always	@(posedge CLK)
begin
	if (IN && !OUT)
		begin
		ctr0 <= 0;
		ctr1 <= ctr1 + 1;
		end
	//	
	if (!IN && OUT)
		begin
		ctr0 <= ctr0 + 1;
		ctr1 <= 0;
		end	
	//
	if (ctr0 == FILTER)
		begin
		ctr0 <= 0;
		ctr1 <= 0;
		OUT <= 0;
		end
	//
	if (ctr1 == FILTER)
		begin
		ctr0 <= 0;
		ctr1 <= 0;
		OUT <= 1;
		end
	//	
	if (((ctr0 > 0) && IN) || ((ctr1 > 0) && !IN))
		begin
		ctr0 <= 0;
		ctr1 <= 0;
		end	
end
endmodule
////////////////////////////////////////////////////////////////////////////////////////////

embedded/fpga/FPGA_BLP_V3_BB_MAX1000_01_00/src/UART/ICARUS_TB.v
`include "UART.v"
// http://verilogtutorial.blogspot.ch/2012/09/verilog-timescale-system-tasks.html
`timescale 10ns/1ns
//
module ICARUS_TB;
	integer file;
	reg clk;
	reg rxd;
	wire [255:0] data_out;
	wire data_write_copy;
	wire [7:0] bank;
	//
	
	initial 
		begin
			clk <= 1;
			rxd <= 1;	
			//
			$dumpfile("vcd\\\icarus_tb.vcd"); 
			$dumpvars(0, ICARUS_TB); 
			//
			#90 rxd <= 1;
			//
			// 0x3C => <
			#108 rxd <= 0;// startbit
			#108 rxd <= 1;// bit 0
			#108 rxd <= 0;// bit 1
			#108 rxd <= 1;// bit 2
			#108 rxd <= 0;// bit 3
			#108 rxd <= 1;// bit 4
			#108 rxd <= 0;// bit 5
			#108 rxd <= 1;// bit 6
			#108 rxd <= 0;// bit 7
			#108 rxd <= 1;// stopbit
			/*
			#108 rxd <= 0;// startbit
			#108 rxd <= 0;// bit 0
			#108 rxd <= 0;// bit 1
			#108 rxd <= 1;// bit 2
			#108 rxd <= 1;// bit 3
			#108 rxd <= 1;// bit 4
			#108 rxd <= 1;// bit 5
			#108 rxd <= 0;// bit 6
			#108 rxd <= 0;// bit 7
			#108 rxd <= 1;// stopbit
			*/
			//	
			// BANK 0x30 => 0
			#108 rxd <= 0;// startbit
			#108 rxd <= 0;// bit 0
			#108 rxd <= 0;// bit 1
			#108 rxd <= 0;// bit 2
			#108 rxd <= 0;// bit 3
			#108 rxd <= 1;// bit 4
			#108 rxd <= 1;// bit 5
			#108 rxd <= 0;// bit 6
			#108 rxd <= 0;// bit 7
			#108 rxd <= 1;// stopbit
			//			
			// 0x31 => 1
			#108 rxd <= 0;// startbit
			#108 rxd <= 1;// bit 0
			#108 rxd <= 0;// bit 1
			#108 rxd <= 0;// bit 2
			#108 rxd <= 0;// bit 3
			#108 rxd <= 1;// bit 4
			#108 rxd <= 1;// bit 5
			#108 rxd <= 0;// bit 6
			#108 rxd <= 0;// bit 7
			#108 rxd <= 1;// stopbit
			//	
			// Daten 0x32 => 2
			#108 rxd <= 0;// startbit
			#108 rxd <= 0;// bit 0
			#108 rxd <= 1;// bit 1
			#108 rxd <= 0;// bit 2
			#108 rxd <= 0;// bit 3
			#108 rxd <= 1;// bit 4
			#108 rxd <= 1;// bit 5
			#108 rxd <= 0;// bit 6
			#108 rxd <= 0;// bit 7
			#108 rxd <= 1;// stopbit
			//			
			// 0x30 => 0
			#108 rxd <= 0;// startbit
			#108 rxd <= 0;// bit 0
			#108 rxd <= 0;// bit 1
			#108 rxd <= 0;// bit 2
			#108 rxd <= 0;// bit 3
			#108 rxd <= 1;// bit 4
			#108 rxd <= 1;// bit 5
			#108 rxd <= 0;// bit 6
			#108 rxd <= 0;// bit 7
			#108 rxd <= 1;// stopbit
			//	
			// 0x3E => >
			#108 rxd <= 0;// startbit
			#108 rxd <= 0;// bit 0
			#108 rxd <= 1;// bit 1
			#108 rxd <= 1;// bit 2
			#108 rxd <= 1;// bit 3
			#108 rxd <= 1;// bit 4
			#108 rxd <= 1;// bit 5
			#108 rxd <= 0;// bit 6
			#108 rxd <= 0;// bit 7
			#108 rxd <= 1;// stopbit
			//	
			#10000 $finish; 
		end 
	//
	always #1 clk <= !clk;
	//
	UART uart(clk, rxd, data_out, data_write_copy, bank);
endmodule
/*
cd D:\Dropbox\ABBTS_LABOR_DOZ\NETZFREQUENZ\QUARTUS\FREQUENZMESSUNG\src\CLOCK\WDT
C:\iverilog\bin\iverilog -s ICARUS_TB -o icarus_tb.o ICARUS_TB.v
C:\iverilog\bin\vvp icarus_tb.o
*/

embedded/fpga/FPGA_BLP_V3_BB_MAX1000_01_00/src/UART/vcd/icarus_tb.vcd
$date
	Fri Aug 24 15:51:11 2018
$end
$version
	Icarus Verilog
$end
$timescale
	1ns
$end
$scope module ICARUS_TB $end
$var wire 1 ! data_write_copy $end
$var wire 256 " data_out [255:0] $end
$var wire 8 # bank [7:0] $end
$var reg 1 $ clk $end
$var reg 1 % rxd $end
$scope module uart $end
$var wire 1 $ CLK $end
$var wire 1 % RXD $end
$var wire 1 & done $end
$var wire 8 ' byte_value [7:0] $end
$var reg 8 ( BANK [7:0] $end
$var reg 256 ) DATA_OUT [255:0] $end
$var reg 1 ! DATA_WRITE_COPY $end
$var reg 8 * bit_offset [7:0] $end
$var reg 8 + byte_ctr [7:0] $end
$var reg 8 , byte_even [7:0] $end
$var reg 8 - byte_even_odd [7:0] $end
$var reg 8 . byte_odd [7:0] $end
$var reg 1 / uart_frg $end
$var reg 4 0 write_data [3:0] $end
$scope module uart_rxd_byte $end
$var wire 1 $ CLK $end
$var wire 1 % RXD $end
$var wire 1 1 imp_start $end
$var wire 1 2 rxd_ $end
$var reg 8 3 BYTE_VALUE [7:0] $end
$var reg 1 & DONE $end
$var reg 8 4 bit_ctr [7:0] $end
$var reg 8 5 bit_sync_ctr [7:0] $end
$var reg 1 6 hri1 $end
$var reg 1 7 hri2 $end
$var reg 1 8 latch_bit $end
$var reg 1 9 uart_frg $end
$scope module uart_inp_filter $end
$var wire 1 $ CLK $end
$var wire 1 % IN $end
$var reg 1 2 OUT $end
$var reg 5 : ctr0 [4:0] $end
$var reg 5 ; ctr1 [4:0] $end
$upscope $end
$upscope $end
$upscope $end
$upscope $end
$enddefinitions $end
#0
$dumpvars
b1 ;
b0 :
09
08
07
06
b0 5
b0 4
b0 3
02
01
b0 0
0/
b0 .
b0 -
b0 ,
b0 +
b0 *
b0 )
b0 (
b0 '
0&
1%
1$
b0 #
b0 "
0!
$end
#10
0$
#20
12
b0 ;
1$
#30
0$
#40
16
1$
#50
0$
#60
17
1$
#70
0$
#80
1$
#90
0$
#100
1$
#110
0$
#120
1$
#130
0$
#140
1$
#150
0$
#160
1$
#170
0$
#180
1$
#190
0$
#200
1$
#210
0$
#220
1$
#230
0$
#240
1$
#250
0$
#260
1$
#270
0$
#280
1$
#290
0$
#300
1$
#310
0$
#320
1$
#330
0$
#340
1$
#350
0$
#360
1$
#370
0$
#380
1$
#390
0$
#400
1$
#410
0$
#420
1$
#430
0$
#440
1$
#450
0$
#460
1$
#470
0$
#480
1$
#490
0$
#500
1$
#510
0$
#520
1$
#530
0$
#540
1$
#550
0$
#560
1$
#570
0$
#580
1$
#590
0$
#600
1$
#610
0$
#620
1$
#630
0$
#640
1$
#650
0$
#660
1$
#670
0$
#680
1$
#690
0$
#700
1$
#710
0$
#720
1$
#730
0$
#740
1$
#750
0$
#760
1$
#770
0$
#780
1$
#790
0$
#800
1$
#810
0$
#820
1$
#830
0$
#840
1$
#850
0$
#860
1$
#870
0$
#880
1$
#890
0$
#900
1$
#910
0$
#920
1$
#930
0$
#940
1$
#950
0$
#960
1$
#970
0$
#980
1$
#990
0$
#1000
1$
#1010
0$
#1020
1$
#1030
0$
#1040
1$
#1050
0$
#1060
1$
#1070
0$
#1080
1$
#1090
0$
#1100
1$
#1110
0$
#1120
1$
#1130
0$
#1140
1$
#1150
0$
#1160
1$
#1170
0$
#1180
1$
#1190
0$
#1200
1$
#1210
0$
#1220
1$
#1230
0$
#1240
1$
#1250
0$
#1260
1$
#1270
0$
#1280
1$
#1290
0$
#1300
1$
#1310
0$
#1320
1$
#1330
0$
#1340
1$
#1350
0$
#1360
1$
#1370
0$
#1380
1$
#1390
0$
#1400
1$
#1410
0$
#1420
1$
#1430
0$
#1440
1$
#1450
0$
#1460
1$
#1470
0$
#1480
1$
#1490
0$
#1500
1$
#1510
0$
#1520
1$
#1530
0$
#1540
1$
#1550
0$
#1560
1$
#1570
0$
#1580
1$
#1590
0$
#1600
1$
#1610
0$
#1620
1$
#1630
0$
#1640
1$
#1650
0$
#1660
1$
#1670
0$
#1680
1$
#1690
0$
#1700
1$
#1710
0$
#1720
1$
#1730
0$
#1740
1$
#1750
0$
#1760
1$
#1770
0$
#1780
1$
#1790
0$
#1800
1$
#1810
0$
#1820
1$
#1830
0$
#1840
1$
#1850
0$
#1860
1$
#1870
0$
#1880
1$
#1890
0$
#1900
1$
#1910
0$
#1920
1$
#1930
0$
#1940
1$
#1950
0$
#1960
1$
#1970
0$
#1980
b1 :
1$
0%
#1990
0$
#2000
02
b0 :
1$
#2010
0$
#2020
11
06
1$
#2030
0$
#2040
01
b1001110 5
19
07
1$
#2050
0$
#2060
b1001101 5
1$
#2070
0$
#2080
b1001100 5
1$
#2090
0$
#2100
b1001011 5
1$
#2110
0$
#2120
b1001010 5
1$
#2130
0$
#2140
b1001001 5
1$
#2150
0$
#2160
b1001000 5
1$
#2170
0$
#2180
b1000111 5
1$
#2190
0$
#2200
b1000110 5
1$
#2210
0$
#2220
b1000101 5
1$
#2230
0$
#2240
b1000100 5
1$
#2250
0$
#2260
b1000011 5
1$
#2270
0$
#2280
b1000010 5
1$
#2290
0$
#2300
b1000001 5
1$
#2310
0$
#2320
b1000000 5
1$
#2330
0$
#2340
b111111 5
1$
#2350
0$
#2360
b111110 5
1$
#2370
0$
#2380
b111101 5
1$
#2390
0$
#2400
b111100 5
1$
#2410
0$
#2420
b111011 5
1$
#2430
0$
#2440
b111010 5
1$
#2450
0$
#2460
b111001 5
1$
#2470
0$
#2480
b111000 5
1$
#2490
0$
#2500
b110111 5
1$
#2510
0$
#2520
b110110 5
1$
#2530
0$
#2540
b110101 5
1$
#2550
0$
#2560
b110100 5
1$
#2570
0$
#2580
b110011 5
1$
#2590
0$
#2600
b110010 5
1$
#2610
0$
#2620
b110001 5
1$
#2630
0$
#2640
b110000 5
1$
#2650
0$
#2660
b101111 5
1$
#2670
0$
#2680
b101110 5
1$
#2690
0$
#2700
b101101 5
1$
#2710
0$
#2720
b101100 5
1$
#2730
0$
#2740
b101011 5
1$
#2750
0$
#2760
b101010 5
1$
#2770
0$
#2780
b101001 5
1$
#2790
0$
#2800
b101000 5
1$
#2810
0$
#2820
b100111 5
1$
#2830
0$
#2840
b100110 5
1$
#2850
0$
#2860
b100101 5
1$
#2870
0$
#2880
b100100 5
1$
#2890
0$
#2900
b100011 5
1$
#2910
0$
#2920
b100010 5
1$
#2930
0$
#2940
b100001 5
1$
#2950
0$
#2960
b100000 5
1$
#2970
0$
#2980
b11111 5
1$
#2990
0$
#3000
b11110 5
1$
#3010
0$
#3020
b11101 5
1$
#3030
0$
#3040
b11100 5
1$
#3050
0$
#3060
b11011 5
b1 ;
1$
1%
#3070
0$
#3080
12
b0 ;
b11010 5
1$
#3090
0$
#3100
b11001 5
1$
#3110
0$
#3120
b11000 5
1$
#3130
0$
#3140
b10111 5
1$
#3150
0$
#3160
b10110 5
1$
#3170
0$
#3180
b10101 5
1$
#3190
0$
#3200
b10100 5
1$
#3210
0$
#3220
b10011 5
1$
#3230
0$
#3240
b10010 5
1$
#3250
0$
#3260
b10001 5
1$
#3270
0$
#3280
b10000 5
1$
#3290
0$
#3300
b1111 5
1$
#3310
0$
#3320
b1110 5
1$
#3330
0$
#3340
b1101 5
1$
#3350
0$
#3360
b1100 5
1$
#3370
0$
#3380
b1011 5
1$
#3390
0$
#3400
b1010 5
1$
#3410
0$
#3420
b1001 5
1$
#3430
0$
#3440
b1000 5
1$
#3450
0$
#3460
b111 5
1$
#3470
0$
#3480
b110 5
1$
#3490
0$
#3500
b101 5
1$
#3510
0$
#3520
b100 5
1$
#3530
0$
#3540
b11 5
1$
#3550
0$
#3560
b10 5
1$
#3570
0$
#3580
b1 5
1$
#3590
0$
#3600
b0 5
1$
#3610
0$
#3620
18
b110101 5
b1 4
b1 '
b1 3
1$
#3630
0$
#3640
08
b110100 5
1$
#3650
0$
#3660
b110011 5
1$
#3670
0$
#3680
b110010 5
1$
#3690
0$
#3700
b110001 5
1$
#3710
0$
#3720
b110000 5
1$
#3730
0$
#3740
b101111 5
1$
#3750
0$
#3760
b101110 5
1$
#3770
0$
#3780
b101101 5
1$
#3790
0$
#3800
b101100 5
1$
#3810
0$
#3820
b101011 5
1$
#3830
0$
#3840
b101010 5
1$
#3850
0$
#3860
b101001 5
1$
#3870
0$
#3880
b101000 5
1$
#3890
0$
#3900
b100111 5
1$
#3910
0$
#3920
b100110 5
1$
#3930
0$
#3940
b100101 5
1$
#3950
0$
#3960
b100100 5
1$
#3970
0$
#3980
b100011 5
1$
#3990
0$
#4000
b100010 5
1$
#4010
0$
#4020
b100001 5
1$
#4030
0$
#4040
b100000 5
1$
#4050
0$
#4060
b11111 5
1$
#4070
0$
#4080
b11110 5
1$
#4090
0$
#4100
b11101 5
1$
#4110
0$
#4120
b11100 5
1$
#4130
0$
#4140
b11011 5
b1 :
1$
0%
#4150
0$
#4160
02
b0 :
b11010 5
1$
#4170
0$
#4180
b11001 5
1$
#4190
0$
#4200
b11000 5
1$
#4210
0$
#4220
b10111 5
1$
#4230
0$
#4240
b10110 5
1$
#4250
0$
#4260
b10101 5
1$
#4270
0$
#4280
b10100 5
1$
#4290
0$
#4300
b10011 5
1$
#4310
0$
#4320
b10010 5
1$
#4330
0$
#4340
b10001 5
1$
#4350
0$
#4360
b10000 5
1$
#4370
0$
#4380
b1111 5
1$
#4390
0$
#4400
b1110 5
1$
#4410
0$
#4420
b1101 5
1$
#4430
0$
#4440
b1100 5
1$
#4450
0$
#4460
b1011 5
1$
#4470
0$
#4480
b1010 5
1$
#4490
0$
#4500
b1001 5
1$
#4510
0$
#4520
b1000 5
1$
#4530
0$
#4540
b111 5
1$
#4550
0$
#4560
b110 5
1$
#4570
0$
#4580
b101 5
1$
#4590
0$
#4600
b100 5
1$
#4610
0$
#4620
b11 5
1$
#4630
0$
#4640
b10 5
1$
#4650
0$
#4660
b1 5
1$
#4670
0$
#4680
b0 5
1$
#4690
0$
#4700
18
b110101 5
b10 4
1$
#4710
0$
#4720
08
b110100 5
1$
#4730
0$
#4740
b110011 5
1$
#4750
0$
#4760
b110010 5
1$
#4770
0$
#4780
b110001 5
1$
#4790
0$
#4800
b110000 5
1$
#4810
0$
#4820
b101111 5
1$
#4830
0$
#4840
b101110 5
1$
#4850
0$
#4860
b101101 5
1$
#4870
0$
#4880
b101100 5
1$
#4890
0$
#4900
b101011 5
1$
#4910
0$
#4920
b101010 5
1$
#4930
0$
#4940
b101001 5
1$
#4950
0$
#4960
b101000 5
1$
#4970
0$
#4980
b100111 5
1$
#4990
0$
#5000
b100110 5
1$
#5010
0$
#5020
b100101 5
1$
#5030
0$
#5040
b100100 5
1$
#5050
0$
#5060
b100011 5
1$
#5070
0$
#5080
b100010 5
1$
#5090
0$
#5100
b100001 5
1$
#5110
0$
#5120
b100000 5
1$
#5130
0$
#5140
b11111 5
1$
#5150
0$
#5160
b11110 5
1$
#5170
0$
#5180
b11101 5
1$
#5190
0$
#5200
b11100 5
1$
#5210
0$
#5220
b11011 5
b1 ;
1$
1%
#5230
0$
#5240
12
b0 ;
b11010 5
1$
#5250
0$
#5260
b11001 5
1$
#5270
0$
#5280
b11000 5
1$
#5290
0$
#5300
b10111 5
1$
#5310
0$
#5320
b10110 5
1$
#5330
0$
#5340
b10101 5
1$
#5350
0$
#5360
b10100 5
1$
#5370
0$
#5380
b10011 5
1$
#5390
0$
#5400
b10010 5
1$
#5410
0$
#5420
b10001 5
1$
#5430
0$
#5440
b10000 5
1$
#5450
0$
#5460
b1111 5
1$
#5470
0$
#5480
b1110 5
1$
#5490
0$
#5500
b1101 5
1$
#5510
0$
#5520
b1100 5
1$
#5530
0$
#5540
b1011 5
1$
#5550
0$
#5560
b1010 5
1$
#5570
0$
#5580
b1001 5
1$
#5590
0$
#5600
b1000 5
1$
#5610
0$
#5620
b111 5
1$
#5630
0$
#5640
b110 5
1$
#5650
0$
#5660
b101 5
1$
#5670
0$
#5680
b100 5
1$
#5690
0$
#5700
b11 5
1$
#5710
0$
#5720
b10 5
1$
#5730
0$
#5740
b1 5
1$
#5750
0$
#5760
b0 5
1$
#5770
0$
#5780
18
b110101 5
b11 4
b101 '
b101 3
1$
#5790
0$
#5800
08
b110100 5
1$
#5810
0$
#5820
b110011 5
1$
#5830
0$
#5840
b110010 5
1$
#5850
0$
#5860
b110001 5
1$
#5870
0$
#5880
b110000 5
1$
#5890
0$
#5900
b101111 5
1$
#5910
0$
#5920
b101110 5
1$
#5930
0$
#5940
b101101 5
1$
#5950
0$
#5960
b101100 5
1$
#5970
0$
#5980
b101011 5
1$
#5990
0$
#6000
b101010 5
1$
#6010
0$
#6020
b101001 5
1$
#6030
0$
#6040
b101000 5
1$
#6050
0$
#6060
b100111 5
1$
#6070
0$
#6080
b100110 5
1$
#6090
0$
#6100
b100101 5
1$
#6110
0$
#6120
b100100 5
1$
#6130
0$
#6140
b100011 5
1$
#6150
0$
#6160
b100010 5
1$
#6170
0$
#6180
b100001 5
1$
#6190
0$
#6200
b100000 5
1$
#6210
0$
#6220
b11111 5
1$
#6230
0$
#6240
b11110 5
1$
#6250
0$
#6260
b11101 5
1$
#6270
0$
#6280
b11100 5
1$
#6290
0$
#6300
b11011 5
b1 :
1$
0%
#6310
0$
#6320
02
b0 :
b11010 5
1$
#6330
0$
#6340
b11001 5
1$
#6350
0$
#6360
b11000 5
1$
#6370
0$
#6380
b10111 5
1$
#6390
0$
#6400
b10110 5
1$
#6410
0$
#6420
b10101 5
1$
#6430
0$
#6440
b10100 5
1$
#6450
0$
#6460
b10011 5
1$
#6470
0$
#6480
b10010 5
1$
#6490
0$
#6500
b10001 5
1$
#6510
0$
#6520
b10000 5
1$
#6530
0$
#6540
b1111 5
1$
#6550
0$
#6560
b1110 5
1$
#6570
0$
#6580
b1101 5
1$
#6590
0$
#6600
b1100 5
1$
#6610
0$
#6620
b1011 5
1$
#6630
0$
#6640
b1010 5
1$
#6650
0$
#6660
b1001 5
1$
#6670
0$
#6680
b1000 5
1$
#6690
0$
#6700
b111 5
1$
#6710
0$
#6720
b110 5
1$
#6730
0$
#6740
b101 5
1$
#6750
0$
#6760
b100 5
1$
#6770
0$
#6780
b11 5
1$
#6790
0$
#6800
b10 5
1$
#6810
0$
#6820
b1 5
1$
#6830
0$
#6840
b0 5
1$
#6850
0$
#6860
18
b110101 5
b100 4
1$
#6870
0$
#6880
08
b110100 5
1$
#6890
0$
#6900
b110011 5
1$
#6910
0$
#6920
b110010 5
1$
#6930
0$
#6940
b110001 5
1$
#6950
0$
#6960
b110000 5
1$
#6970
0$
#6980
b101111 5
1$
#6990
0$
#7000
b101110 5
1$
#7010
0$
#7020
b101101 5
1$
#7030
0$
#7040
b101100 5
1$
#7050
0$
#7060
b101011 5
1$
#7070
0$
#7080
b101010 5
1$
#7090
0$
#7100
b101001 5
1$
#7110
0$
#7120
b101000 5
1$
#7130
0$
#7140
b100111 5
1$
#7150
0$
#7160
b100110 5
1$
#7170
0$
#7180
b100101 5
1$
#7190
0$
#7200
b100100 5
1$
#7210
0$
#7220
b100011 5
1$
#7230
0$
#7240
b100010 5
1$
#7250
0$
#7260
b100001 5
1$
#7270
0$
#7280
b100000 5
1$
#7290
0$
#7300
b11111 5
1$
#7310
0$
#7320
b11110 5
1$
#7330
0$
#7340
b11101 5
1$
#7350
0$
#7360
b11100 5
1$
#7370
0$
#7380
b11011 5
b1 ;
1$
1%
#7390
0$
#7400
12
b0 ;
b11010 5
1$
#7410
0$
#7420
b11001 5
1$
#7430
0$
#7440
b11000 5
1$
#7450
0$
#7460
b10111 5
1$
#7470
0$
#7480
b10110 5
1$
#7490
0$
#7500
b10101 5
1$
#7510
0$
#7520
b10100 5
1$
#7530
0$
#7540
b10011 5
1$
#7550
0$
#7560
b10010 5
1$
#7570
0$
#7580
b10001 5
1$
#7590
0$
#7600
b10000 5
1$
#7610
0$
#7620
b1111 5
1$
#7630
0$
#7640
b1110 5
1$
#7650
0$
#7660
b1101 5
1$
#7670
0$
#7680
b1100 5
1$
#7690
0$
#7700
b1011 5
1$
#7710
0$
#7720
b1010 5
1$
#7730
0$
#7740
b1001 5
1$
#7750
0$
#7760
b1000 5
1$
#7770
0$
#7780
b111 5
1$
#7790
0$
#7800
b110 5
1$
#7810
0$
#7820
b101 5
1$
#7830
0$
#7840
b100 5
1$
#7850
0$
#7860
b11 5
1$
#7870
0$
#7880
b10 5
1$
#7890
0$
#7900
b1 5
1$
#7910
0$
#7920
b0 5
1$
#7930
0$
#7940
18
b110101 5
b101 4
b10101 '
b10101 3
1$
#7950
0$
#7960
08
b110100 5
1$
#7970
0$
#7980
b110011 5
1$
#7990
0$
#8000
b110010 5
1$
#8010
0$
#8020
b110001 5
1$
#8030
0$
#8040
b110000 5
1$
#8050
0$
#8060
b101111 5
1$
#8070
0$
#8080
b101110 5
1$
#8090
0$
#8100
b101101 5
1$
#8110
0$
#8120
b101100 5
1$
#8130
0$
#8140
b101011 5
1$
#8150
0$
#8160
b101010 5
1$
#8170
0$
#8180
b101001 5
1$
#8190
0$
#8200
b101000 5
1$
#8210
0$
#8220
b100111 5
1$
#8230
0$
#8240
b100110 5
1$
#8250
0$
#8260
b100101 5
1$
#8270
0$
#8280
b100100 5
1$
#8290
0$
#8300
b100011 5
1$
#8310
0$
#8320
b100010 5
1$
#8330
0$
#8340
b100001 5
1$
#8350
0$
#8360
b100000 5
1$
#8370
0$
#8380
b11111 5
1$
#8390
0$
#8400
b11110 5
1$
#8410
0$
#8420
b11101 5
1$
#8430
0$
#8440
b11100 5
1$
#8450
0$
#8460
b11011 5
b1 :
1$
0%
#8470
0$
#8480
02
b0 :
b11010 5
1$
#8490
0$
#8500
b11001 5
1$
#8510
0$
#8520
b11000 5
1$
#8530
0$
#8540
b10111 5
1$
#8550
0$
#8560
b10110 5
1$
#8570
0$
#8580
b10101 5
1$
#8590
0$
#8600
b10100 5
1$
#8610
0$
#8620
b10011 5
1$
#8630
0$
#8640
b10010 5
1$
#8650
0$
#8660
b10001 5
1$
#8670
0$
#8680
b10000 5
1$
#8690
0$
#8700
b1111 5
1$
#8710
0$
#8720
b1110 5
1$
#8730
0$
#8740
b1101 5
1$
#8750
0$
#8760
b1100 5
1$
#8770
0$
#8780
b1011 5
1$
#8790
0$
#8800
b1010 5
1$
#8810
0$
#8820
b1001 5
1$
#8830
0$
#8840
b1000 5
1$
#8850
0$
#8860
b111 5
1$
#8870
0$
